aiorun.py
aiorun-2024.5.1.dist-info/LICENSE
aiorun-2024.5.1.dist-info/WHEEL
aiorun-2024.5.1.dist-info/METADATA
aiorun-2024.5.1.dist-info/RECORD
