Metadata-Version: 2.1
Name: aiorun
Version: 2024.5.1
Summary: Boilerplate for asyncio applications
Home-page: https://github.com/cjrh/aiorun
Author: Caleb Hattingh
Author-email: caleb.hattingh@gmail.com
Requires-Python: >=3.7
Classifier: License :: OSI Approved :: Apache Software License
Classifier: Natural Language :: English
Classifier: Programming Language :: Python
Classifier: Programming Language :: Python :: 3.8
Classifier: Programming Language :: Python :: 3.9
Classifier: Programming Language :: Python :: 3.10
Classifier: Programming Language :: Python :: 3.11
Classifier: Programming Language :: Python :: 3.12
Classifier: Operating System :: OS Independent
Requires-Dist: pytest ; extra == "dev"
Requires-Dist: pytest-cov ; extra == "dev"
Provides-Extra: dev
